PLC/AudioTools.py
PLC/DatabaseTools.py
PLC/FilmTools.py
PLC/MovieGenerator.py
PLC/PyQtTools.py
PLC/TextToVoiceApi.py
PLC/TextTools.py
PLC/Tools.py
PLC/__init__.py
PLC-0.1.9.dist-info/METADATA
PLC-0.1.9.dist-info/WHEEL
PLC-0.1.9.dist-info/top_level.txt
PLC-0.1.9.dist-info/RECORD
