Metadata-Version: 2.1
Name: PLC
Version: 0.1.9
Summary: Local Package for Parsian Language Center
Home-page: https://github.com/KingURL/PLC
Author: Amirhossein Bagheri
Author-email: Amirbagheri@protonmail.com
License: UNKNOWN
Platform: UNKNOWN
Classifier: Programming Language :: Python :: 3
Classifier: Operating System :: OS Independent
